pytubethumbs/__init__.py
pytubethumbs/main.py
pytubethumbs/src.py
pytubethumbs-0.0.33.dist-info/LICENSE
pytubethumbs-0.0.33.dist-info/METADATA
pytubethumbs-0.0.33.dist-info/WHEEL
pytubethumbs-0.0.33.dist-info/top_level.txt
pytubethumbs-0.0.33.dist-info/RECORD
