Metadata-Version: 2.1
Name: pytubethumbs
Version: 0.0.33
Summary: It is a library that helps you create thumbnails for your YouTube channel
Author: Free Python Code (Amr Elgarhy)
Author-email: <amr.ee@yahoo.com>
Keywords: python,thumbnails,images,youtube
Classifier: Development Status :: 1 - Planning
Classifier: Intended Audience :: Developers
Classifier: Programming Language :: Python :: 3
Classifier: Operating System :: Unix
Classifier: Operating System :: MacOS :: MacOS X
Classifier: Operating System :: Microsoft :: Windows
License-File: LICENSE
Requires-Dist: Pillow
